pquisby/__init__.py
pquisby/command/__init__.py
pquisby/command/compare_benchmark.py
pquisby/command/main.py
pquisby/command/process_benchmark.py
pquisby/lib/__init__.py
pquisby/lib/compare_sheets.py
pquisby/lib/post_processing.py
pquisby/lib/process_result.py
pquisby/lib/util.py
pquisby/lib/benchmarks/__init__.py
pquisby/lib/benchmarks/fio/__init__.py
pquisby/lib/benchmarks/fio/comparison.py
pquisby/lib/benchmarks/fio/fio.py
pquisby/lib/benchmarks/fio/graph.py
pquisby/lib/benchmarks/fio/summary.py
pquisby/lib/benchmarks/uperf/__init__.py
pquisby/lib/benchmarks/uperf/comparison.py
pquisby/lib/benchmarks/uperf/graph.py
pquisby/lib/benchmarks/uperf/uperf.py
pquisby/lib/credentials/__init__.py
pquisby/lib/credentials/creds.py
pquisby/lib/logging/__init__.py
pquisby/lib/logging/logging_configure.py
pquisby/lib/pricing/__init__.py
pquisby/lib/pricing/cloud_pricing.py
pquisby/lib/sheet/__init__.py
pquisby/lib/sheet/sheet_util.py
pquisby/lib/sheet/sheetapi.py
pquisby-0.0.28.dist-info/LICENSE
pquisby-0.0.28.dist-info/METADATA
pquisby-0.0.28.dist-info/WHEEL
pquisby-0.0.28.dist-info/entry_points.txt
pquisby-0.0.28.dist-info/top_level.txt
pquisby-0.0.28.dist-info/RECORD
